sqlalchemy_multiple_db/__init__.py
sqlalchemy_multiple_db/helper.py
sqlalchemy_multiple_db/version.py
tests/__init__.py
tests/test_helper.py
sqlalchemy_multiple_db-2.1.1.dist-info/LICENSE
sqlalchemy_multiple_db-2.1.1.dist-info/METADATA
sqlalchemy_multiple_db-2.1.1.dist-info/WHEEL
sqlalchemy_multiple_db-2.1.1.dist-info/top_level.txt
sqlalchemy_multiple_db-2.1.1.dist-info/RECORD
